Metadata-Version: 1.0
Name: distributionsBG
Version: 2.1
Summary: Gaussian and Binomial distributions
Home-page: UNKNOWN
Author: Svitlana Konopatska
Author-email: svetlana_viktorovna@meta.ua
License: UNKNOWN
Platform: UNKNOWN
